Metadata-Version: 2.1
Name: pysecrecy
Version: 1.0.0
Summary: a way to make your life easier
Home-page: https://github.com/batestin1/
Author: Bates
Author-email: Bates@mailer.com.br
Project-URL: Codigo fonte, https://github.com/batestin1/
Project-URL: Download, https://github.com/batestin1/
Keywords: a way to make your life easier
